{
  "posts": [
    {
      "id": 1,
      "title": "Digital Assets: The Real Estate of Virtual Worlds",
      "slug": "digital-assets-virtual-worlds",
      "author": "System Admin",
      "date": "2025-10-12",
      "readTime": 12,
      "tags": ["digital","assets","strategy"],
      "excerpt": "Modern enterprise is shifting from physical assets to digital logic.",
      "content": "<p>Digital real estate isn't just a URL; it's the attention-vector of your target demographic...</p>",
      "featuredImage": "blog-1.svg"
    }
  ]
}
